tarjimonuzbek/__init__.py
tarjimonuzbek-0.0.1.dist-info/METADATA
tarjimonuzbek-0.0.1.dist-info/WHEEL
tarjimonuzbek-0.0.1.dist-info/top_level.txt
tarjimonuzbek-0.0.1.dist-info/RECORD
