Metadata-Version: 2.1
Name: tarjimonuzbek
Version: 0.0.1
Summary: Ushbu kutubxona tarjima qilish uchun ishlatiladi
Author: Hikmatullayev Islombek
Author-email: gimlerpro8899@gmail.com
